<blocks app="Snap! 4.0, http://snap.berkeley.edu" version="1"><block-definition s="data reporterr" type="command" category="sensing"><header/><code/><inputs/><script><block s="doSetVar"><l>datalist</l><block s="reportNewList"><list><l>-1</l><l>-26.13</l><l>-79.04</l><l>-2</l><l>-26.15</l><l>-79.06</l><l>-3</l><l>-26.16</l><l>-79.08</l><l>-4</l><l>-26.17</l><l>-79.10</l><l>-5</l><l>-26.16</l><l>-79.08</l><l>-6</l><l>-26.16</l><l>-79.08</l><l>-7</l><l>-26.16</l><l>-79.08</l><l>-8</l><l>-26.15</l><l>-79.06</l><l>-9</l><l>-26.16</l><l>-79.08</l><l>-10</l><l>-26.15</l><l>-79.06</l><l>-11</l><l>-26.15</l><l>-79.06</l><l>-12</l><l>-26.13</l><l>-79.04</l><l>-13</l><l>-26.12</l><l>-79.02</l><l>-14</l><l>-26.12</l><l>-79.02</l><l>-15</l><l>-26.12</l><l>-79.02</l><l>-16</l><l>-26.11</l><l>-79.00</l><l>-1</l><l>-26.08</l><l>-78.95</l><l>-58.01</l><l>-2</l><l>-26.08</l><l>-78.95</l><l>-57.89</l><l>-3</l><l>-26.09</l><l>-78.96</l><l>-58.03</l><l>-4</l><l>-26.09</l><l>-78.96</l><l>-58.09</l><l>-5</l><l>-26.11</l><l>-79.00</l><l>-60.11</l><l>-6</l><l>-26.11</l><l>-79.00</l><l>-60.48</l><l>-7</l><l>-26.11</l><l>-79.00</l><l>-60.15</l><l>-8</l><l>-26.11</l><l>-79.00</l><l>-59.86</l><l>-9</l><l>-26.12</l><l>-79.02</l><l>-59.89</l><l>-10</l><l>-26.15</l><l>-79.06</l><l>-60.06</l><l>-11</l><l>-26.16</l><l>-79.08</l><l>-59.64</l><l>-12</l><l>-26.16</l><l>-79.08</l><l>-58.69</l><l>-1</l><l>-26.17</l><l>-79.10</l><l>-57.67</l><l>-2</l><l>-26.16</l><l>-79.08</l><l>-57.27</l><l>-3</l><l>-26.17</l><l>-79.10</l><l>-57.06</l><l>-4</l><l>-26.15</l><l>-79.06</l><l>-57.20</l><l>-5</l><l>-26.17</l><l>-79.10</l><l>-57.37</l><l>-6</l><l>-26.17</l><l>-79.10</l><l>-57.57</l><l>-7</l><l>-26.36</l><l>-79.45</l><l>-64.63</l><l>-8</l><l>-27.99</l><l>-82.38</l><l>-83.79</l><l>-9</l><l>-28.78</l><l>-83.81</l><l>-90.79</l><l>-10</l><l>-29.37</l><l>-84.87</l><l>-93.64</l><l>-11</l><l>-29.86</l><l>-85.74</l><l>-94.62</l><l>-12</l><l>-30.30</l><l>-86.53</l><l>-94.76</l><l>-13</l><l>-30.68</l><l>-87.23</l><l>-94.47</l><l>-14</l><l>-31.00</l><l>-87.81</l><l>-94.08</l><l>-15</l><l>-31.29</l><l>-88.33</l><l>-93.66</l><l>-16</l><l>-31.52</l><l>-88.73</l><l>-93.27</l><l>-17</l><l>-31.72</l><l>-89.10</l><l>-92.91</l><l>-18</l><l>-31.92</l><l>-89.45</l><l>-92.59</l><l>-19</l><l>-32.04</l><l>-89.68</l><l>-92.32</l><l>-20</l><l>-32.18</l><l>-89.93</l><l>-92.08</l><l>-21</l><l>-32.30</l><l>-90.14</l><l>-91.86</l><l>-22</l><l>-32.41</l><l>-90.34</l><l>-91.68</l><l>-23</l><l>-32.63</l><l>-90.74</l><l>-94.49</l><l>-24</l><l>-32.19</l><l>-89.95</l><l>-86.14</l><l>-25</l><l>-32.05</l><l>-89.70</l><l>-77.92</l><l>-26</l><l>-31.98</l><l>-89.56</l><l>-69.78</l><l>-27</l><l>-31.89</l><l>-89.41</l><l>-63.11</l><l>-28</l><l>-31.82</l><l>-89.27</l><l>-57.08</l><l>-29</l><l>-31.71</l><l>-89.08</l><l>-53.24</l><l>-30</l><l>-31.61</l><l>-88.91</l><l>-50.08</l><l>-31</l><l>-31.50</l><l>-88.69</l><l>-47.62</l><l>-32</l><l>-31.39</l><l>-88.50</l><l>-46.28</l><l>-1</l><l>-26.32</l><l>-79.37</l><l>-21.80</l><l>-2</l><l>-26.32</l><l>-79.37</l><l>-21.43</l><l>-1</l><l>-26.31</l><l>-79.35</l><l>-17.95</l><l>-2</l><l>-26.31</l><l>-79.35</l><l>-17.66</l><l>-3</l><l>-26.31</l><l>-79.35</l><l>-20.28</l><l>-4</l><l>-26.31</l><l>-79.35</l><l>-22.72</l><l>-5</l><l>-26.32</l><l>-79.37</l><l>-22.97</l><l>-6</l><l>-26.32</l><l>-79.37</l><l>-22.40</l><l>-7</l><l>-26.32</l><l>-79.37</l><l>-22.36</l><l>-8</l><l>-26.31</l><l>-79.35</l><l>-21.14</l><l>-9</l><l>-26.31</l><l>-79.35</l><l>-21.59</l><l>-10</l><l>-26.31</l><l>-79.35</l><l>-22.17</l><l>-11</l><l>-26.31</l><l>-79.35</l><l>-21.10</l><l>-12</l><l>-26.32</l><l>-79.37</l><l>-21.21</l><l>-13</l><l>-26.30</l><l>-79.33</l><l>-20.89</l><l>-14</l><l>-26.31</l><l>-79.35</l><l>-21.73</l><l>-15</l><l>-26.31</l><l>-79.35</l><l>-21.79</l><l>-16</l><l>-26.31</l><l>-79.35</l><l>-21.53</l><l>-17</l><l>-26.31</l><l>-79.35</l><l>-22.27</l><l>-18</l><l>-26.31</l><l>-79.35</l><l>-22.76</l><l>-19</l><l>-26.32</l><l>-79.37</l><l>-21.70</l><l>-20</l><l>-26.31</l><l>-79.35</l><l>-21.24</l><l>-21</l><l>-26.31</l><l>-79.35</l><l>-21.32</l><l>-22</l><l>-26.34</l><l>-79.41</l><l>-22.04</l><l>-23</l><l>-26.70</l><l>-80.06</l><l>-48.90</l><l>-24</l><l>-27.43</l><l>-81.38</l><l>-74.57</l><l>-25</l><l>-27.82</l><l>-82.07</l><l>-86.67</l><l>-26</l><l>-28.11</l><l>-82.59</l><l>-92.77</l><l>-27</l><l>-28.38</l><l>-83.08</l><l>-95.88</l><l>-28</l><l>-28.59</l><l>-83.46</l><l>-97.50</l><l>-29</l><l>-28.15</l><l>-82.67</l><l>-88.17</l><l>-30</l><l>-29.53</l><l>-85.16</l><l>-100.77</l><l>-31</l><l>-28.87</l><l>-83.96</l><l>-100.36</l><l>-32</l><l>-28.50</l><l>-83.31</l><l>-96.26</l><l>-33</l><l>-28.21</l><l>-82.79</l><l>-86.56</l><l>-34</l><l>-28.13</l><l>-82.63</l><l>-66.93</l><l>-35</l><l>-28.14</l><l>-82.65</l><l>-50.01</l><l>-36</l><l>-28.11</l><l>-82.59</l><l>-38.75</l><l>-37</l><l>-28.10</l><l>-82.57</l><l>-30.75</l><l>-38</l><l>-28.03</l><l>-82.46</l><l>-26.97</l><l>-39</l><l>-28.00</l><l>-82.40</l><l>-21.86</l><l>-40</l><l>-27.94</l><l>-82.29</l><l>-23.40</l><l>-41</l><l>-27.88</l><l>-82.19</l><l>-21.09</l><l>-42</l><l>-27.85</l><l>-82.13</l><l>-18.54</l><l>-43</l><l>-27.80</l><l>-82.03</l><l>-20.50</l><l>-44</l><l>-27.74</l><l>-81.94</l><l>-21.31</l><l>-45</l><l>-27.70</l><l>-81.86</l><l>-20.49</l><l>-46</l><l>-27.66</l><l>-81.78</l><l>-19.99</l><l>-47</l><l>-27.57</l><l>-81.63</l><l>-21.55</l><l>-48</l><l>-27.52</l><l>-81.53</l><l>-21.68</l><l>-49</l><l>-27.50</l><l>-81.49</l><l>-19.89</l><l>-50</l><l>-27.46</l><l>-81.44</l><l>-19.92</l><l>-51</l><l>-27.40</l><l>-81.32</l><l>-21.98</l><l>-52</l><l>-27.37</l><l>-81.26</l><l>-20.15</l><l>-53</l><l>-27.34</l><l>-81.20</l><l>-19.47</l><l>-54</l><l>-27.26</l><l>-81.07</l><l>-21.89</l><l>-55</l><l>-27.24</l><l>-81.03</l><l>-20.96</l><l>-56</l><l>-27.21</l><l>-80.97</l><l>-20.27</l><l>-57</l><l>-27.16</l><l>-80.90</l><l>-20.53</l><l>-58</l><l>-27.11</l><l>-80.80</l><l>-20.36</l><l>-59</l><l>-27.08</l><l>-80.74</l><l>-19.51</l><l>-60</l><l>-27.05</l><l>-80.68</l><l>-20.15</l><l>-61</l><l>-27.00</l><l>-80.61</l><l>-18.02</l><l>-62</l><l>-26.97</l><l>-80.55</l><l>-17.07</l><l>-63</l><l>-26.95</l><l>-80.51</l><l>-17.15</l><l>-64</l><l>-26.93</l><l>-80.47</l><l>-17.42</l><l>-65</l><l>-26.90</l><l>-80.41</l><l>-17.71</l><l>-66</l><l>-26.86</l><l>-80.35</l><l>-17.95</l><l>-67</l><l>-26.81</l><l>-80.26</l><l>-17.66</l><l>-68</l><l>-26.77</l><l>-80.18</l><l>-16.15</l><l>-69</l><l>-26.73</l><l>-80.12</l><l>-16.65</l><l>-70</l><l>-26.72</l><l>-80.10</l><l>-16.12</l><l>-71</l><l>-26.67</l><l>-80.01</l><l>-15.35</l><l>-72</l><l>-26.65</l><l>-79.97</l><l>-18.56</l><l>-73</l><l>-26.63</l><l>-79.93</l><l>-18.13</l><l>-74</l><l>-26.61</l><l>-79.89</l><l>-17.74</l><l>-75</l><l>-26.58</l><l>-79.85</l><l>-17.34</l><l>-76</l><l>-26.56</l><l>-79.81</l><l>-16.42</l><l>-77</l><l>-26.53</l><l>-79.76</l><l>-16.16</l><l>-78</l><l>-26.51</l><l>-79.72</l><l>-16.37</l><l>-79</l><l>-26.48</l><l>-79.66</l><l>-20.23</l><l>-80</l><l>-26.46</l><l>-79.62</l><l>-21.68</l><l>-81</l><l>-26.42</l><l>-79.56</l><l>-19.49</l><l>-82</l><l>-26.39</l><l>-79.51</l><l>-19.42</l><l>-83</l><l>-26.36</l><l>-79.45</l><l>-20.01</l><l>-84</l><l>-26.33</l><l>-79.39</l><l>-21.87</l><l>-85</l><l>-26.32</l><l>-79.37</l><l>-20.33</l><l>-86</l><l>-26.31</l><l>-79.35</l><l>-18.96</l><l>-87</l><l>-26.26</l><l>-79.27</l><l>-19.30</l><l>-88</l><l>-26.25</l><l>-79.25</l><l>-20.08</l></list></block></block></script></block-definition></blocks>